LICENSE
README.md
setup.py
mergin/__init__.py
mergin/cert.pem
mergin/cli.py
mergin/client.py
mergin/client_pull.py
mergin/client_push.py
mergin/common.py
mergin/editor.py
mergin/merginproject.py
mergin/report.py
mergin/utils.py
mergin/version.py
mergin/test/__init__.py
mergin/test/sqlite_con.py
mergin/test/test_client.py
mergin/test/test_push_logging.py
mergin_client.egg-info/PKG-INFO
mergin_client.egg-info/SOURCES.txt
mergin_client.egg-info/dependency_links.txt
mergin_client.egg-info/entry_points.txt
mergin_client.egg-info/requires.txt
mergin_client.egg-info/top_level.txt