Metadata-Version: 2.4
Name: mergin-client
Version: 0.11.0
Summary: Mergin Maps utils and client
Home-page: https://github.com/MerginMaps/python-api-client
Author: Lutra Consulting Ltd.
Author-email: info@merginmaps.com
License: MIT
Platform: any
Classifier: Development Status :: 5 - Production/Stable
Classifier: Intended Audience :: Developers
Classifier: License :: OSI Approved :: MIT License
Classifier: Operating System :: OS Independent
Classifier: Programming Language :: Python :: 3
License-File: LICENSE
Requires-Dist: python-dateutil==2.8.2
Requires-Dist: pygeodiff==2.0.4
Requires-Dist: pytz==2022.1
Requires-Dist: click==8.1.3
Dynamic: author
Dynamic: author-email
Dynamic: classifier
Dynamic: description
Dynamic: home-page
Dynamic: license
Dynamic: license-file
Dynamic: platform
Dynamic: requires-dist
Dynamic: summary
